smartchem_ion3/__init__.py
smartchem_ion3-1.0.0.dist-info/LICENSE.txt
smartchem_ion3-1.0.0.dist-info/METADATA
smartchem_ion3-1.0.0.dist-info/WHEEL
smartchem_ion3-1.0.0.dist-info/top_level.txt
smartchem_ion3-1.0.0.dist-info/RECORD
