Metadata-Version: 2.1
Name: smartchem-ion3
Version: 1.0.0
Summary: Python interface to the SMARTChem-Ion3 ion-selective electrode instrument.
Home-page: https://gitlab.com/ptapping/smartchem-ion3
Author: Patrick Tapping
Author-email: mail@patricktapping.com
License: UNKNOWN
Project-URL: Documentation, https://smartchem-ion3.readthedocs.io/
Project-URL: Source, https://gitlab.com/ptapping/smartchem-ion3
Project-URL: Tracker, https://gitlab.com/ptapping/smartchem-ion3/-/issues
Platform: UNKNOWN
Classifier: Programming Language :: Python :: 3
Classifier: License :: OSI Approved :: GNU General Public License v3 or later (GPLv3+)
Classifier: Operating System :: OS Independent
Requires-Python: >=3.9
License-File: LICENSE.txt
Requires-Dist: pyserial
